LICENSE
README.md
setup.cfg
setup.py
IHSBotballKit/__init__.py
IHSBotballKit/bot.py
IHSBotballKit/camera.py
IHSBotballKit/config_loader.py
IHSBotballKit/controller.py
IHSBotballKit/create.py
IHSBotballKit/create_extras.py
IHSBotballKit/motor.py
IHSBotballKit/motors_extras.py
IHSBotballKit/runner.py
IHSBotballKit/sensor.py
IHSBotballKit/servo.py
IHSBotballKit.egg-info/PKG-INFO
IHSBotballKit.egg-info/SOURCES.txt
IHSBotballKit.egg-info/dependency_links.txt
IHSBotballKit.egg-info/requires.txt
IHSBotballKit.egg-info/top_level.txt