Metadata-Version: 2.1
Name: IHSBotballKit
Version: 1.0.1
Summary: An object-oriented wrapper for the KIPR Botball library with additional functionalities.
Home-page: https://github.com/snow4060
Author: snow4060
Author-email: haoyun807963@gmail.com
License: GPL-3.0
Download-URL: https://github.com/ihsrobotics/IHSBotballKit/archive/refs/tags/1.0.1.tar.gz
Keywords: KIPR,BOTBALL,WOMBAT,LIBKIPR,LIBWALLABY
Platform: UNKNOWN
Classifier: Development Status :: 4 - Beta
Classifier: Intended Audience :: Developers
Classifier: Topic :: Software Development :: Build Tools
Classifier: License :: OSI Approved :: GNU General Public License v3 (GPLv3)
Classifier: Programming Language :: Python :: 3
License-File: LICENSE
